get_cdk/__init__.py
get_cdk/main.py
get_cdk-2025.6.0.dist-info/METADATA
get_cdk-2025.6.0.dist-info/WHEEL
get_cdk-2025.6.0.dist-info/entry_points.txt
get_cdk-2025.6.0.dist-info/RECORD
