Metadata-Version: 2.3
Name: get-cdk
Version: 2025.6.0
Summary: Helper script for installing shinnytech cdk
License: MIT
Author: shinny-taojiachun
Author-email: taojiachun@shinnytech.com
Requires-Python: >=3.9
Classifier: License :: OSI Approved :: MIT License
Classifier: Programming Language :: Python :: 3
Classifier: Programming Language :: Python :: 3.9
Classifier: Programming Language :: Python :: 3.10
Classifier: Programming Language :: Python :: 3.11
Classifier: Programming Language :: Python :: 3.12
Classifier: Programming Language :: Python :: 3.13
Requires-Dist: gitpython (==3.1.18)
Requires-Dist: oss2 (>=2.18.0,<3.0.0)
Requires-Dist: packaging (>=24.1,<25.0)
Requires-Dist: shinny-structlog (>=0.0.4,<0.0.5)
